Workbook

Sheet Project Portfolio
A1: Project ID | B1: Project Name | C1: Project Manager | D1: Business Unit | E1: Phase | F1: Priority | G1: Start Date | H1: End Date | I1: Planned Duration (Days) | J1: % Complete | K1: Budget (₹ Lakhs) | L1: Spent (₹ Lakhs) | M1: Budget Variance (₹ Lakhs) | N1: Planned Tasks | O1: Completed Tasks | P1: Open Issues | Q1: RAG Status | R1: Notes
A2: PRJ-001 | B2: Core Banking Modernization | C2: Anita Sharma | D2: Technology | E2: Execution | F2: High | G2: 01-Jan-2025 | H2: 31-Dec-2025 | I2: 365 | J2: 62 | K2: 850 | L2: 530 | M2: =K2-L2 -> 320 | N2: 48 | O2: 30 | P2: 3 | Q2: Green | R2: On track, Phase 2 go-live in Q3
A3: PRJ-002 | B3: Regulatory Compliance Suite | C3: Rajesh Nair | D3: Risk & Compliance | E3: Execution | F3: Critical | G3: 01-Mar-2025 | H3: 30-Sep-2025 | I3: 214 | J3: 45 | K3: 320 | L3: 160 | M3: =K3-L3 -> 160 | N3: 30 | O3: 14 | P3: 7 | Q3: Amber | R3: Delay in vendor deliverable - watchlist
A4: PRJ-003 | B4: Data Warehouse Migration | C4: Priya Menon | D4: Data & Analytics | E4: Planning | F4: High | G4: 15-Apr-2025 | H4: 31-Mar-2026 | I4: 351 | J4: 18 | K4: 480 | L4: 90 | M4: =K4-L4 -> 390 | N4: 60 | O4: 11 | P4: 2 | Q4: Green | R4: Kick-off done; resource onboarding in progress
A5: PRJ-004 | B5: CRM Platform Upgrade | C5: Vikram Desai | D5: Sales & Distribution | E5: Execution | F5: Medium | G5: 01-Feb-2025 | H5: 31-Aug-2025 | I5: 212 | J5: 70 | K5: 220 | L5: 165 | M5: =K5-L5 -> 55 | N5: 40 | O5: 28 | P5: 5 | Q5: Amber | R5: Integration testing delayed by 2 weeks
A6: PRJ-005 | B6: HRMS Self-Service Portal | C6: Sunita Joshi | D6: HR | E6: UAT | F6: Medium | G6: 01-Nov-2024 | H6: 30-Jun-2025 | I6: 241 | J6: 88 | K6: 110 | L6: 100 | M6: =K6-L6 -> 10 | N6: 35 | O6: 31 | P6: 1 | Q6: Green | R6: UAT sign-off expected by end of June
A7: PRJ-006 | B7: Cybersecurity Enhancement | C7: Amit Kulkarni | D7: IT Security | E7: Execution | F7: Critical | G7: 01-Jan-2025 | H7: 31-Oct-2025 | I7: 304 | J7: 50 | K7: 600 | L7: 310 | M7: =K7-L7 -> 290 | N7: 50 | O7: 25 | P7: 9 | Q7: Red | R7: 3 critical vulnerabilities open; escalated to CISO
A8: PRJ-007 | B8: Mobile Banking App v3 | C8: Neha Kapoor | D8: Digital Banking | E8: Execution | F8: High | G8: 01-Mar-2025 | H8: 30-Nov-2025 | I8: 275 | J8: 40 | K8: 375 | L8: 150 | M8: =K8-L8 -> 225 | N8: 44 | O8: 18 | P8: 4 | Q8: Green | R8: Feature freeze planned for Aug
A9: PRJ-008 | B9: ERP Finance Module | C9: Ramesh Iyer | D9: Finance | E9: Initiation | F9: Low | G9: 01-Jun-2025 | H9: 31-May-2026 | I9: 365 | J9: 5 | K9: 290 | L9: 15 | M9: =K9-L9 -> 275 | N9: 20 | O9: 1 | P9: 0 | Q9: Green | R9: PMC charter approved; team being formed
A10: PRJ-009 | B10: Cloud Infrastructure Setup | C10: Pooja Tiwari | D10: IT Infrastructure | E10: Execution | F10: High | G10: 15-Feb-2025 | H10: 15-Aug-2025 | I10: 181 | J10: 75 | K10: 520 | L10: 410 | M10: =K10-L10 -> 110 | N10: 36 | O10: 27 | P10: 6 | Q10: Amber | R10: Budget overrun risk; mitigation plan in review
A11: PRJ-010 | B11: Customer Analytics Platform | C11: Sanjay Mehta | D11: Data & Analytics | E11: Execution | F11: High | G11: 01-Apr-2025 | H11: 31-Jan-2026 | I11: 306 | J11: 30 | K11: 410 | L11: 125 | M11: =K11-L11 -> 285 | N11: 55 | O11: 17 | P11: 2 | Q11: Green | R11: ML model training underway
A12: PRJ-011 | B12: ATM Network Upgrade | C12: Kavita Rao | D12: Operations | E12: Execution | F12: Medium | G12: 01-Mar-2025 | H12: 30-Sep-2025 | I12: 214 | J12: 55 | K12: 180 | L12: 102 | M12: =K12-L12 -> 78 | N12: 30 | O12: 17 | P12: 3 | Q12: Green | R12: 30 of 55 ATM locations completed
A13: PRJ-012 | B13: Payment Gateway Integration | C13: Arjun Bose | D13: Payments | E13: Closed | F13: High | G13: 01-Oct-2024 | H13: 31-Mar-2025 | I13: 182 | J13: 100 | K13: 150 | L13: 148 | M13: =K13-L13 -> 2 | N13: 28 | O13: 28 | P13: 0 | Q13: Green | R13: Successfully closed; post-implementation review done
... A16: PRJ-015 | B16: Treasury Management System | C16: Nalini Suresh | D16: Finance | E16: Execution | F16: High | G16: 15-Jan-2025 | H16: 15-Nov-2025 | I16: 305 | J16: 60 | K16: 490 | L16: 300 | M16: =K16-L16 -> 190 | N16: 38 | O16: 23 | P16: 5 | Q16: Amber | R16: Integration with Bloomberg feed delayed

Sheet Portfolio Summary
A1: 📊 Portfolio Summary Dashboard
A4: 📁 Project Overview
A5: Total Projects | B5: =COUNTA('Project Portfolio'!A2:A16) -> 15
A6: Green Status | B6: =COUNTIF('Project Portfolio'!Q2:Q16,"Green") -> 9
A7: Amber Status | B7: =COUNTIF('Project Portfolio'!Q2:Q16,"Amber") -> 5
A8: Red Status | B8: =COUNTIF('Project Portfolio'!Q2:Q16,"Red") -> 1
A9: Closed Projects | B9: =COUNTIF('Project Portfolio'!E2:E16,"Closed") -> 1
A11: 💰 Budget Overview
A12: Total Budget (₹ Lakhs) | B12: =SUM('Project Portfolio'!K2:K16) -> 5795
A13: Total Spent (₹ Lakhs) | B13: =SUM('Project Portfolio'!L2:L16) -> 2845
A14: Total Variance (₹ Lakhs) | B14: =SUM('Project Portfolio'!M2:M16) -> 2950
A15: Budget Utilization % | B15: =ROUND(SUM('Project Portfolio'!L2:L16)/SUM('Project Portfolio'!K2:K16)*100,1) -> 49.1
A17: 🚨 Risk & Issues
A18: Critical Projects | B18: =COUNTIF('Project Portfolio'!F2:F16,"Critical") -> 3
A19: Total Open Issues | B19: =SUM('Project Portfolio'!P2:P16) -> 56
A20: Projects with Issues > 5 | B20: =COUNTIF('Project Portfolio'!P2:P16,">5") -> 4
A22: 📅 Delivery Health
A23: Avg % Complete | B23: =ROUND(AVERAGE('Project Portfolio'!J2:J16),1) -> 49.7
A24: Projects > 75% Complete | B24: =COUNTIF('Project Portfolio'!J2:J16,">75") -> 2
A25: Projects < 20% Complete | B25: =COUNTIF('Project Portfolio'!J2:J16,"<20") -> 3

Sheet Insights Summary
A1: 📊 Project Portfolio Insights Summary
A3: 🔴 INSIGHT 1: Critical Projects Carry Highest Risk & Issues
A4: The 3 Critical priority projects (Regulatory Compliance, Cybersecurity, Fraud Detection AI) account for ₹1,480 Lakhs (26% of total budget) but have 24 open issues combined—43% of all portfolio issues. The Cybersecurity Enhancement project is the only RED status project with 9 open issues and 3 critical vulnerabilities escalated to CISO.
A6: 💰 INSIGHT 2: Low Budget Utilization (49%) Despite Projects Being 50% Through Timeline
A7: Total portfolio budget is ₹5,795 Lakhs with only ₹2,845 Lakhs spent (49.1%). Cloud Infrastructure Setup shows budget overrun risk (₹410L spent at 75% complete on ₹520L budget), while Data Warehouse Migration has significant unspent budget (₹390L variance at only 18% complete). This signals uneven execution pacing across the portfolio.
A9: ⚠️ INSIGHT 3: 6 Projects (40%) Are Amber/Red – All in Execution Phase
A10: 5 Amber + 1 Red projects represent ₹2,470 Lakhs (43% of budget). All 6 at-risk projects are in Execution phase, suggesting systemic delivery challenges—vendor delays, integration issues, and model accuracy problems. External dependencies are cited as root causes in multiple projects.
A32: 🔍 Questions for Deeper Analysis
A33: 1. Would you like a timeline/Gantt view of project delivery dates to identify scheduling conflicts?
A34: 2. Should we analyze which Project Managers have the most at-risk projects?
A35: 3. Would a budget burn-down forecast help identify which projects may exceed budget?
A36: 4. Do you want to drill into Business Unit performance (e.g., Risk & Compliance has 2 Amber projects)?
A37: 5. Should we create a risk matrix plotting Open Issues vs Budget size to prioritize interventions?

Sheet Project Timeline
A1: 📅 Project Timeline / Gantt View
H2: 45566 | I2: 45597 | J2: 45627 | K2: 45658 | L2: 45689 | M2: 45717 | N2: 45748 | O2: 45778 | P2: 45809 | Q2: 45839 | R2: 45870 | S2: 45901 | T2: 45931 | U2: 45962 | V2: 45992 | W2: 46023 | X2: 46054 | Y2: 46082 | Z2: 46113 | AA2: 46143
A3: Project Name | B3: Start | C3: End | D3: Days | E3: %Done | F3: RAG | G3: Phase | H3: Oct'24 | I3: Nov'24 | J3: Dec'24 | K3: Jan'25 | L3: Feb'25 | M3: Mar'25 | N3: Apr'25 | O3: May'25 | P3: Jun'25 | Q3: Jul'25 | R3: Aug'25 | S3: Sep'25 | T3: Oct'25 | U3: Nov'25 | V3: Dec'25 | W3: Jan'26 | X3: Feb'26 | Y3: Mar'26 | Z3: Apr'26 | AA3: May'26
A4: ='Project Portfolio'!B13 -> Payment Gateway Integration | B4: ='Project Portfolio'!G13 -> 01-Oct-2024 | C4: ='Project Portfolio'!H13 -> 31-Mar-2025 | D4: ='Project Portfolio'!I13 -> 182 | E4: ='Project Portfolio'!J13/100 -> 1 | F4: ='Project Portfolio'!Q13 -> Green | G4: ='Project Portfolio'!E13 -> Closed | H4: █ | I4: █ | J4: █ | K4: █ | L4: █ | M4: █
A5: ='Project Portfolio'!B6 -> HRMS Self-Service Portal | B5: ='Project Portfolio'!G6 -> 01-Nov-2024 | C5: ='Project Portfolio'!H6 -> 30-Jun-2025 | D5: ='Project Portfolio'!I6 -> 241 | E5: ='Project Portfolio'!J6/100 -> 0.88 | F5: ='Project Portfolio'!Q6 -> Green | G5: ='Project Portfolio'!E6 -> UAT | I5: █ | J5: █ | K5: █ | L5: █ | M5: █ | N5: █ | O5: █ | P5: █
A6: ='Project Portfolio'!B2 -> Core Banking Modernization | B6: ='Project Portfolio'!G2 -> 01-Jan-2025 | C6: ='Project Portfolio'!H2 -> 31-Dec-2025 | D6: ='Project Portfolio'!I2 -> 365 | E6: ='Project Portfolio'!J2/100 -> 0.62 | F6: ='Project Portfolio'!Q2 -> Green | G6: ='Project Portfolio'!E2 -> Execution | K6: █ | L6: █ | M6: █ | N6: █ | O6: █ | P6: █ | Q6: █ | R6: █ | S6: █ | T6: █ | U6: █ | V6: █
A7: ='Project Portfolio'!B7 -> Cybersecurity Enhancement | B7: ='Project Portfolio'!G7 -> 01-Jan-2025 | C7: ='Project Portfolio'!H7 -> 31-Oct-2025 | D7: ='Project Portfolio'!I7 -> 304 | E7: ='Project Portfolio'!J7/100 -> 0.5 | F7: ='Project Portfolio'!Q7 -> Red | G7: ='Project Portfolio'!E7 -> Execution | K7: █ | L7: █ | M7: █ | N7: █ | O7: █ | P7: █ | Q7: █ | R7: █ | S7: █ | T7: █
A8: ='Project Portfolio'!B16 -> Treasury Management System | B8: ='Project Portfolio'!G16 -> 15-Jan-2025 | C8: ='Project Portfolio'!H16 -> 15-Nov-2025 | D8: ='Project Portfolio'!I16 -> 305 | E8: ='Project Portfolio'!J16/100 -> 0.6 | F8: ='Project Portfolio'!Q16 -> Amber | G8: ='Project Portfolio'!E16 -> Execution | K8: █ | L8: █ | M8: █ | N8: █ | O8: █ | P8: █ | Q8: █ | R8: █ | S8: █ | T8: █ | U8: █
A9: ='Project Portfolio'!B5 -> CRM Platform Upgrade | B9: ='Project Portfolio'!G5 -> 01-Feb-2025 | C9: ='Project Portfolio'!H5 -> 31-Aug-2025 | D9: ='Project Portfolio'!I5 -> 212 | E9: ='Project Portfolio'!J5/100 -> 0.7 | F9: ='Project Portfolio'!Q5 -> Amber | G9: ='Project Portfolio'!E5 -> Execution | L9: █ | M9: █ | N9: █ | O9: █ | P9: █ | Q9: █ | R9: █
A10: ='Project Portfolio'!B14 -> Fraud Detection AI | B10: ='Project Portfolio'!G14 -> 01-Feb-2025 | C10: ='Project Portfolio'!H14 -> 31-Dec-2025 | D10: ='Project Portfolio'!I14 -> 334 | E10: ='Project Portfolio'!J14/100 -> 0.38 | F10: ='Project Portfolio'!Q14 -> Amber | G10: ='Project Portfolio'!E14 -> Execution | L10: █ | M10: █ | N10: █ | O10: █ | P10: █ | Q10: █ | R10: █ | S10: █ | T10: █ | U10: █ | V10: █
A11: ='Project Portfolio'!B10 -> Cloud Infrastructure Setup | B11: ='Project Portfolio'!G10 -> 15-Feb-2025 | C11: ='Project Portfolio'!H10 -> 15-Aug-2025 | D11: ='Project Portfolio'!I10 -> 181 | E11: ='Project Portfolio'!J10/100 -> 0.75 | F11: ='Project Portfolio'!Q10 -> Amber | G11: ='Project Portfolio'!E10 -> Execution | L11: █ | M11: █ | N11: █ | O11: █ | P11: █ | Q11: █ | R11: █
A12: ='Project Portfolio'!B3 -> Regulatory Compliance Suite | B12: ='Project Portfolio'!G3 -> 01-Mar-2025 | C12: ='Project Portfolio'!H3 -> 30-Sep-2025 | D12: ='Project Portfolio'!I3 -> 214 | E12: ='Project Portfolio'!J3/100 -> 0.45 | F12: ='Project Portfolio'!Q3 -> Amber | G12: ='Project Portfolio'!E3 -> Execution | L12: █ | M12: █ | N12: █ | O12: █ | P12: █ | Q12: █ | R12: █ | S12: █
A13: ='Project Portfolio'!B8 -> Mobile Banking App v3 | B13: ='Project Portfolio'!G8 -> 01-Mar-2025 | C13: ='Project Portfolio'!H8 -> 30-Nov-2025 | D13: ='Project Portfolio'!I8 -> 275 | E13: ='Project Portfolio'!J8/100 -> 0.4 | F13: ='Project Portfolio'!Q8 -> Green | G13: ='Project Portfolio'!E8 -> Execution | L13: █ | M13: █ | N13: █ | O13: █ | P13: █ | Q13: █ | R13: █ | S13: █ | T13: █ | U13: █
A14: ='Project Portfolio'!B12 -> ATM Network Upgrade | B14: ='Project Portfolio'!G12 -> 01-Mar-2025 | C14: ='Project Portfolio'!H12 -> 30-Sep-2025 | D14: ='Project Portfolio'!I12 -> 214 | E14: ='Project Portfolio'!J12/100 -> 0.55 | F14: ='Project Portfolio'!Q12 -> Green | G14: ='Project Portfolio'!E12 -> Execution | L14: █ | M14: █ | N14: █ | O14: █ | P14: █ | Q14: █ | R14: █ | S14: █
A15: ='Project Portfolio'!B11 -> Customer Analytics Platform | B15: ='Project Portfolio'!G11 -> 01-Apr-2025 | C15: ='Project Portfolio'!H11 -> 31-Jan-2026 | D15: ='Project Portfolio'!I11 -> 306 | E15: ='Project Portfolio'!J11/100 -> 0.3 | F15: ='Project Portfolio'!Q11 -> Green | G15: ='Project Portfolio'!E11 -> Execution | N15: █ | O15: █ | P15: █ | Q15: █ | R15: █ | S15: █ | T15: █ | U15: █ | V15: █ | W15: █
A16: ='Project Portfolio'!B4 -> Data Warehouse Migration | B16: ='Project Portfolio'!G4 -> 15-Apr-2025 | C16: ='Project Portfolio'!H4 -> 31-Mar-2026 | D16: ='Project Portfolio'!I4 -> 351 | E16: ='Project Portfolio'!J4/100 -> 0.18 | F16: ='Project Portfolio'!Q4 -> Green | G16: ='Project Portfolio'!E4 -> Planning | N16: █ | O16: █ | P16: █ | Q16: █ | R16: █ | S16: █ | T16: █ | U16: █ | V16: █ | W16: █ | X16: █ | Y16: █
A17: ='Project Portfolio'!B15 -> Branch Digitization | B17: ='Project Portfolio'!G15 -> 01-May-2025 | C17: ='Project Portfolio'!H15 -> 30-Apr-2026 | D17: ='Project Portfolio'!I15 -> 365 | E17: ='Project Portfolio'!J15/100 -> 0.1 | F17: ='Project Portfolio'!Q15 -> Green | G17: ='Project Portfolio'!E15 -> Planning | N17: █ | O17: █ | P17: █ | Q17: █ | R17: █ | S17: █ | T17: █ | U17: █ | V17: █ | W17: █ | X17: █ | Y17: █ | Z17: █ | AA17: █
A18: ='Project Portfolio'!B9 -> ERP Finance Module | B18: ='Project Portfolio'!G9 -> 01-Jun-2025 | C18: ='Project Portfolio'!H9 -> 31-May-2026 | D18: ='Project Portfolio'!I9 -> 365 | E18: ='Project Portfolio'!J9/100 -> 0.05 | F18: ='Project Portfolio'!Q9 -> Green | G18: ='Project Portfolio'!E9 -> Initiation | P18: █ | Q18: █ | R18: █ | S18: █ | T18: █ | U18: █ | V18: █ | W18: █ | X18: █ | Y18: █ | Z18: █ | AA18: █
A20: 📍 Today: May 28, 2025
A22: Legend: | B22: █ Green | C22: █ Amber | D22: █ Red
A24: ⚠️ Scheduling Observations
A25: • Peak Overlap (Mar-Sep 2025): 11 projects running concurrently — high resource contention risk
A26: • Q3 2025 Crunch: 6 projects ending Aug-Oct including 2 Critical priority — potential delivery bottleneck
A27: • At-Risk Projects (Amber/Red): All concentrated in execution phase with overlapping timelines
A28: • Long-running projects (Data Warehouse, ERP Finance, Branch Digitization) extend well into 2026
